ytcomment/auth.py
ytcomment/comment.py
ytcomment/uploads.py
YoutTubeComments-0.3.dist-info/METADATA
YoutTubeComments-0.3.dist-info/WHEEL
YoutTubeComments-0.3.dist-info/top_level.txt
YoutTubeComments-0.3.dist-info/RECORD
