Metadata-Version: 2.1
Name: YoutTubeComments
Version: 0.3
Summary: A wrapper to comment on videos via your account!
Home-page: UNKNOWN
Author: KeinShin
Author-email: <ytcomments@ytcomments.com>
License: UNKNOWN
Keywords: python,youtube,scraper,youtube,comments,commentyoutubevideo
Platform: UNKNOWN
Classifier: Development Status :: 1 - Planning
Classifier: Intended Audience :: Developers
Classifier: Programming Language :: Python :: 3
Classifier: Operating System :: Unix
Classifier: Operating System :: MacOS :: MacOS X
Classifier: Operating System :: Microsoft :: Windows
Requires-Dist: google-api-python-client (==2.17.0)
Requires-Dist: google-auth (==1.35.0)
Requires-Dist: google-auth-httplib2 (==0.1.0)
Requires-Dist: google-auth-oauthlib (==0.4.5)
Requires-Dist: googleapis-common-protos (==1.53.0)
Requires-Dist: requests (==2.26.0)
